backstage_oauth2/client.py
backstage_oauth2/__init__.py
backstage_oauth2/urls.py
backstage_oauth2/views.py
backstage_oauth2-0.1.8.dist-info/RECORD
backstage_oauth2-0.1.8.dist-info/metadata.json
backstage_oauth2-0.1.8.dist-info/WHEEL
backstage_oauth2-0.1.8.dist-info/DESCRIPTION.rst
backstage_oauth2-0.1.8.dist-info/top_level.txt
backstage_oauth2-0.1.8.dist-info/METADATA
