Metadata-Version: 2.0
Name: backstage-oauth2
Version: 0.1.8
Summary: App de integracao com o login do backstage
Home-page: https://gitlab.globoi.com/dbdev/backstage_oauth2
Author: DBaaS Team
Author-email: dbaas@corp.globo.com
License: BSD
Keywords: backstage_oauth2
Platform: UNKNOWN
Classifier: Development Status :: 2 - Pre-Alpha
Classifier: Intended Audience :: Developers
Classifier: License :: OSI Approved :: BSD License
Classifier: Natural Language :: English
Classifier: Programming Language :: Python :: 2
Classifier: Programming Language :: Python :: 2.6
Classifier: Programming Language :: Python :: 2.7
Classifier: Programming Language :: Python :: 3
Classifier: Programming Language :: Python :: 3.3
Classifier: Programming Language :: Python :: 3.4
Requires-Dist: django (==1.6.10)
Requires-Dist: django-all-access (==0.5.1)
Requires-Dist: requests (==2.5.0)
